WhatsAppBot/__init__.py
whats_app_bot/__init__.py
whats_app_bot-0.0.3.dist-info/LICENSE.txt
whats_app_bot-0.0.3.dist-info/METADATA
whats_app_bot-0.0.3.dist-info/WHEEL
whats_app_bot-0.0.3.dist-info/top_level.txt
whats_app_bot-0.0.3.dist-info/RECORD
