Metadata-Version: 2.1
Name: whats-app-bot
Version: 0.0.3
Summary: For automating whatsapp chats
Home-page: https://github.com/prashantepicprogrammer/WhatsAppBot
Author: Prashant Dwivedi
Author-email: m.prashant.dwivedi@gmail.com
License: UNKNOWN
Platform: UNKNOWN
Classifier: Programming Language :: Python :: 3
Classifier: License :: OSI Approved :: MIT License
Classifier: Operating System :: OS Independent
